FULL_ADDER/full_adder.v
 // ---------- Half Adder Module ----------
module HA(sum, carry, x, y);
  input x, y;
  output sum, carry;

  xor(sum, x, y);
  and(carry, x, y);
endmodule

// structural-----------
module full_adder_st(s,c,a,b,cin);
  input a,b,cin ;
  output s,c ;
  wire N1,N2,N3;
  
  HA HA1 (N1,N2,a,b);
  HA HA2 (s,N3,N1,cin);
  or OR1 (c, N2, N3);
  
endmodule

// dataflow---------

module full_adder_df(s,c,a,b,cin);
  input a,b,cin;
  output s,c;

  assign s= a^b^cin;
  assign c = (a&b)| (cin&(a^b));

endmodule


// behavioral-----------

module full_adder_bh(s,c,a,b,cin);
  input a,b,cin ;
  output reg s,c;
   always @ (*)
   begin 
    s= a^b^cin;
    c = (a&b)| (cin&(a^b));
   end
 endmodule

FULL_ADDER/full_adder_tb.v
`timescale 1ns/1ns
`include "full_adder.v"

module full_adder_tb;
  reg a,b,cin;
  wire c,s;
 

  full_adder_bh full_adder1 (s,c,a,b,cin);
  
   initial begin
    $dumpfile("full_adder.vcd");
    $dumpvars (0,full_adder_tb);

    $monitor ("time=%d \t a=%b \t b=%b \t cin=%b \t s=%b \t c=%b",$time,a,b,cin,s,c);
      #10 a=0; b=0; cin=0;
      #10 a=0; b=0; cin=1;
      #10 a=0; b=1; cin=0;
      #10 a=0; b=1; cin=1;
      #10 a=1; b=0; cin=0;
      #10 a=1; b=0; cin=1;
      #10 a=1; b=1; cin=0;
      #10 a=1; b=1; cin=1;
      #10 $finish;

   end
   endmodule

FULL_ADDER/full_adder.vcd
$date
	Sun Oct 12 09:47:08 2025
$end
$version
	Icarus Verilog
$end
$timescale
	1ns
$end
$scope module full_adder_tb $end
$var wire 1 ! s $end
$var wire 1 " c $end
$var reg 1 # a $end
$var reg 1 $ b $end
$var reg 1 % cin $end
$scope module full_adder1 $end
$var wire 1 # a $end
$var wire 1 $ b $end
$var wire 1 % cin $end
$var reg 1 " c $end
$var reg 1 ! s $end
$upscope $end
$upscope $end
$enddefinitions $end
$comment Show the parameter values. $end
$dumpall
$end
#0
$dumpvars
x%
x$
x#
x"
x!
$end
#10
0"
0!
0%
0$
0#
#20
1!
1%
#30
0%
1$
#40
1"
0!
1%
#50
0"
1!
0%
0$
1#
#60
1"
0!
1%
#70
0%
1$
#80
1!
1%
